itunes_iap-2.5.0.dist-info/DESCRIPTION.rst
itunes_iap-2.5.0.dist-info/METADATA
itunes_iap-2.5.0.dist-info/RECORD
itunes_iap-2.5.0.dist-info/WHEEL
itunes_iap-2.5.0.dist-info/metadata.json
itunes_iap-2.5.0.dist-info/top_level.txt
itunesiap/__init__.py
itunesiap/environment.py
itunesiap/exceptions.py
itunesiap/legacy.py
itunesiap/receipt.py
itunesiap/request.py
itunesiap/shortcut.py
itunesiap/tools.py
itunesiap/verify_aiohttp.py
itunesiap/verify_requests.py
itunesiap/version.txt
