Metadata-Version: 2.0
Name: itunes-iap
Version: 2.5.0
Summary: Apple iTunes In-app purchase verification api.
Home-page: https://github.com/youknowone/itunes-iap
Author: Jeong YunWon
Author-email: itunesiap@youknowone.org
License: UNKNOWN
Platform: UNKNOWN
Classifier: Intended Audience :: Developers
Classifier: Operating System :: OS Independent
Classifier: License :: OSI Approved :: BSD License
Classifier: Programming Language :: Python
Classifier: Programming Language :: Python :: 2
Classifier: Programming Language :: Python :: 2.6
Classifier: Programming Language :: Python :: 2.7
Classifier: Programming Language :: Python :: 3
Classifier: Programming Language :: Python :: 3.3
Classifier: Programming Language :: Python :: 3.4
Classifier: Programming Language :: Python :: 3.5
Classifier: Programming Language :: Python :: 3.6
Requires-Dist: prettyexc (>=0.6.0)
Requires-Dist: python-dateutil
Requires-Dist: pytz
Requires-Dist: requests[security]
Requires-Dist: six
Provides-Extra: doc
Requires-Dist: sphinx; extra == 'doc'
Provides-Extra: tests
Requires-Dist: mock; extra == 'tests'
Requires-Dist: patch; extra == 'tests'
Requires-Dist: pytest (>=3.0.0); extra == 'tests'
Requires-Dist: pytest-cov; extra == 'tests'
Requires-Dist: tox; extra == 'tests'
